axon_conabio/__init__.py
axon_conabio/utils.py
axon_conabio/version.py
axon_conabio/datasets/__init__.py
axon_conabio/datasets/basedataset.py
axon_conabio/datasets/tf_dataset.py
axon_conabio/evaluator/__init__.py
axon_conabio/evaluator/default_config.ini
axon_conabio/evaluator/default_config.yaml
axon_conabio/evaluator/evaluator.py
axon_conabio/evaluator/evaluator_config.py
axon_conabio/losses/__init__.py
axon_conabio/losses/baseloss.py
axon_conabio/management/__init__.py
axon_conabio/management/commands.py
axon_conabio/management/config.py
axon_conabio/management/default_config.ini
axon_conabio/management/default_config.yaml
axon_conabio/management/evaluate.py
axon_conabio/management/make_project.py
axon_conabio/management/train.py
axon_conabio/management/utils.py
axon_conabio/metrics/__init__.py
axon_conabio/metrics/basemetrics.py
axon_conabio/models/__init__.py
axon_conabio/models/basemodel.py
axon_conabio/models/tf_model.py
axon_conabio/preprocessors/__init__.py
axon_conabio/preprocessors/basepreprocessor.py
axon_conabio/products/__init__.py
axon_conabio/products/product.py
axon_conabio/trainer/__init__.py
axon_conabio/trainer/default_config.ini
axon_conabio/trainer/default_config.yaml
axon_conabio/trainer/logger.py
axon_conabio/trainer/tf_trainer.py
axon_conabio/trainer/tf_trainer_config.py
axon_conabio-0.5.1.dist-info/METADATA
axon_conabio-0.5.1.dist-info/RECORD
axon_conabio-0.5.1.dist-info/WHEEL
axon_conabio-0.5.1.dist-info/entry_points.txt
axon_conabio-0.5.1.dist-info/top_level.txt
