Metadata-Version: 2.1
Name: axon-conabio
Version: 0.5.1
Summary: Conjunto de herramientas para crear, entrenar y evaluar modelos.
Home-page: https://github.com/mbsantiago/axon-conabio
Author: Santiago Martínez, Everardo Robredo
Author-email: santiago.mbal@gmail.com
License: UNKNOWN
Platform: UNKNOWN
Classifier: Programming Language :: Python :: 3
Classifier: License :: OSI Approved :: MIT License
Classifier: Operating System :: OS Independent
Requires-Dist: tqdm
Requires-Dist: six
Requires-Dist: click
Requires-Dist: numpy
